{   
    "settings": {
        "_tr": "👉 ÉRINTÉSI GYORSBILLENTYŰK",
        "_tc": "🎨 SZÍNEK",
        "_tt": "🔤 BETŰTÍPUSOK",
        "_ta": "🖼️ AOD BEÁLLÍTÁSOK (Mindig bekapcsolt kijelző)",
        "_to": "💡 EGYÉB",
        "_touch1": "Érintési gyorsbillentyű óra",
        "_touch2": "Érintési gyorsbillentyű perc",
        "_o0": "↔️ Felső elrendezés",
        "_o1": "↔️ Középső elrendezés",
        "_o2": "↔️ Alsó elrendezés",

        "_f1": "Bal felső adatok",
        "_f1l": "Bal felső címke",
        "_s1": "Bal felső haladás",
        "_f2": "Jobb felső adatok",
        "_f2l": "Jobb felső címke",
        "_s2": "Jobb felső haladás",

        "_f3l": "Középső bal címke",
        "_f3": "Középső bal adatok",
        "_g0": "Középső bal eltolás (25=közép)",

        "_f12l": "Középső jobb címke",
        "_f12": "Középső jobb adatok",
        "_g1": "Középső jobb eltolás (25=közép)",
        
        "_f4": "1. sor bal adatok",
        "_f4l": "1. sor bal címke",
        "_f5": "1. sor középső adatok",
        "_f5l": "1. sor középső címke",
        "_f6": "1. sor jobb adatok",
        "_f6l": "1. sor jobb címke",

        "_f7": "2. sor bal adatok",
        "_f7l": "2. sor bal címke",
        "_f8": "2. sor középső adatok",
        "_f8l": "2. sor középső címke",
        "_f9": "2. sor jobb adatok",
        "_f9l": "2. sor jobb címke",

        "_f10": "Alsó adatok",
        "_f10l": "Alsó címke",
        "_f11": "Alsó 2 mező (két alsó mező használatakor)",
        "_f11l": "Alsó 2 címke",

        "_gr": "Grafikon Gradiens",
        "gr0": "Értékfüggő",
        "gr1": "Bal - Jobb",

        "_bgi": "Háttér stílus",
        "bg_detailed": "=== Részletes hátterek: ===",
        "bg0": "Nincs háttér",
        "bg1": "Vas réteg",
        "bg4": "Körvonalak",

        "bg20": "Hatszög",
        "bg21": "Világ",
        "bg22": "Terepminta",
        "bg23": "Ellipszis",
        "bg24": "Egyszerű",

        "bg_simple": "=== Egyszerű hátterek: ===",
        "bg5": "Vonalak (1px)",
        "bg6": "Vonalak (2px)",
        "bg7": "Vonalak (3px)",
        "bg8": "Vonalak (4px)",
        "bg9": "Vonalak (1px elválasztók nélkül)",
        "bg10": "Vonalak (2px elválasztók nélkül)",
        "bg11": "Vonalak (3px elválasztók nélkül)",
        "bg12": "Vonalak (4px elválasztók nélkül)",
        "bg_old": "=== Régi hátterek: ===",
        "bg2": "Vas réteg 2",
        "bg3": "Vas réteg 3",

        "fnt0": "Play félkövér",        
        "fnt1": "Play félkövér nagy",    
        "fnt2": "Play közepes",    
        "fnt3": "Notes",   
        "fnt4": "Barlow",   
        "fnt5": "Digitális",

        "fnt10": "Play félkövér körvonalazott",
        "fnt11": "Play félkövér nagy körvonalazott",
        "fnt12": "Play közepes körvonalazott",
        "fnt13": "Notes körvonalazott",
        "fnt14": "Barlow körvonalazott",
        "fnt15": "Digitális körvonalazott",
        
        "_tfont": "Óra betűtípus",
        "_tfontM": "Perc betűtípus",
        "_tfontAOD": "Idő betűtípus AOD",
        "_tfontS": "Idő betűméret",
        "_tfontsS": "Másodperc betűméret",

        "_sh": "Idő árnyék",
        "sh0": "Nincs árnyék",
        "sh1": "1px",
        "sh2": "2px",
        "sh3": "3px",
        "sh4": "4px",

        "_fb": "Időháttér letiltása (csak nem mips-gradiens)",
        "_fba": "Időháttér letiltása",

        "fnto": "Körvonalazott (ha elérhető)",
        "fnts": "Ugyanaz maradjon",

        "_hf": "Idő betűtípus",
        "_hfa": "Idő betűtípus (AOD, mindig bekapcsolva)",
        "_hfs": "Idő betűméret",

        "_ox": "Idő X eltolás, 50 = közép",
        "_oy": "Idő Y eltolás, 50 = közép",

        "_bftype": "Alsó mezők típusa",
        "_gfont": "Szöveg betűtípus",
        "_gfontS": "Szöveg betűméret",

        "_gradientq": "Színátmenet minősége",
        "mg": "MIPS színátmenet",
        "ng": "Nincs színátmenet",

        "_tfontsp": "Idő betűtípus távolság 50 = alapértelmezett", 
        "_tfontsp3": "Idő X eltolás, 50 = közép",
        "_tfontsp2": "Idő Y eltolás, 50 = közép",

        "_pc": "Szöveg színe",
        "_ic": "Címke színe",

        "_gs": "Diagram megjelenítése vonaldiagramként",
        "_gg": "Grafikon távolság hozzáadása (régi stílus)",
        "_c0": "Diagram",
        "_ccl": "Diagram színe 1",
        "_ccl2": "Diagram színe 2",

        "_bglc": "Háttér árnyalat színe",

        "_b0": "Diagram felül + egy mező alul",
        "_b1": "Diagram alul + egy mező felül",
        "_b2": "Diagram alul + két mező felül",
        "_b3": "Két mező haladássávokkal",

        "_bgc": "Háttér színe",
        "_hc1": "Óra színe",
        "_hc2": "Óra színe 2",
        "_mc1": "Perc színe",
        "_mc2": "Perc színe 2",
        "_dividerC": "Elválasztó színe",
        "_sc": "Középső jobb felső színe",
        "_sc2": "Középső jobb alsó színe",
        "_aas": "Mindig bekapcsolt másodpercek",

        "_crcp": "Haladássáv színe 1",
        "_crcp2": "Haladássáv színe 2",
        "_crcu": "Haladássáv színe kitöltetlen",
        "lcd": "75%-kal sötétebb",

        "_5f": "Mező haladásának megjelenítése",
        "_6f": "Tele",
        "_7f": "Üres",
        "_8f": "Elrejtés",

        "_aod": "AOD mód (Mindig bekapcsolt kijelző)",
        "_aodct": "AOD idő árnyalat színe",
        "_aodc": "AOD adat árnyalat színe",
        "_aodT": "AOD idő fényereje",
        "_aodD": "AOD adat fényereje. Ha a képernyő kikapcsol AOD közben, csökkentse ezt a számot. Alacsonyabb szám = kevesebb akkumulátor-használat, de kevésbé fényes. Lásd GYIK)",
        "_aodS": "AOD eltolás - pixelek száma, amennyivel a képernyő véletlenszerűen elmozdul percenként a beégés megelőzésére)",
        
        "_f20": "AOD mező adatok",
        "_l20": "AOD mező címke",

        "ad0": "Képernyő KIKAPCSOLÁSA",
        "ad100": "Teljes AOD (alapértelmezett)",
        "ad102": "Teljes AOD - fekete háttér - diagramok elrejtése",
        "ad1": "Csak idő",
        "ad2": "Csak idő - középre",
        "ad3": "Csak idő - mozgó",
        "ad4": "Idő + adatmező (válassza alul)",
        "ad5": "Idő középre + adatmező",
        "ad6": "Idő mozgó + adatmező",
        "_aodf1": "",
        "_aodf2": ""
    }
}
