{
    "settings": {
        "_sg": "Αλλαγή κάτω στυλ/γράφημα",
        "_c32": "Διάγραμμα θέσης σελήνης",
        "_c31": "Διάγραμμα θέσης ήλιου",
        "_c30": "Διάγραμμα θέσης ήλιου + σελήνης",
        "_c52": "Πρόγνωση καιρού 4 ημερών",
        "_c53": "Πρόγνωση καιρού 4 ωρών",

        "_c1": "Διάγραμμα / Γράφημα",
        "_c2": "Χρώμα διαγράμματος 1",
        "_c3": "Χρώμα διαγράμματος 2",
        "_c4": "Χρώμα εικονιδίου καιρού επάνω",
        "_c5": "Χρώμα γραμμής προόδου 1",
        "_c6": "Χρώμα γραμμής προόδου 2",
        "_c7": "Χρώμα εικονιδίου ειδοποίησης",
        "_c8": "Χρώμα καντράν",
        "_c9": "Χρώμα γραμμής φόντου",
        "_c10": "Χρώμα φόντου διαγράμματος",

        "_mc1": "Χρώμα δείκτη 1",
        "_mc2": "Χρώμα δείκτη 2",

        "_fo": "Περιγραμμένο (αν διατίθεται)",
        "_fk": "Διατήρηση ίδιου",

        "_md1": "Δεδομένα δείκτη 1",
        "_md2": "Δεδομένα δείκτη 2",

        "_s1": "1. Στυλ επάνω",
        "_f1": "1. Δεδομένα επάνω 1",
        "_l1": "1. Ετικέτα επάνω 1",
        "_f2": "2. Δεδομένα επάνω 2",
        "_l2": "2. Ετικέτα επάνω 2",
        "_f3": "3. Δεδομένα επάνω 3 (πρόοδος)",
        "_l3": "3. Ετικέτα επάνω 3",

        "_f4": "4. Δεδομένα κέντρου 1",
        "_l4": "4. Ετικέτα κέντρου 1",
        "_f5": "5. Δεδομένα κέντρου 2",
        "_l5": "5. Ετικέτα κέντρου 2",
        "_f6": "6. Δεδομένα κέντρου 3",
        "_l6": "6. Ετικέτα κέντρου 3",

        "_s2": "7. Στυλ κάτω",
        "_gs": "7. Διάγραμμα κάτω ως γραμμικό γράφημα",
        "_g2": "7. Διάγραμμα κάτω χρησιμοποιεί χρώμα 2 όταν επιτευχθεί στόχος",
        "_f7": "7. Δεδομένα κάτω 1",
        "_l7": "7. Ετικέτα κάτω 1",
        "_f8": "8. Δεδομένα κάτω 2",
        "_l8": "8. Ετικέτα κάτω 2",
        "_f9": "9. Δεδομένα κάτω 3",
        "_l9": "9. Ετικέτα κάτω 3",

        "_sn": "Αριστερό κέντρο",
        "_sb": "Δεξί κέντρο",

        "_r0": "Εικονίδιο ειδοποίησης",
        "_r1": "Εικονίδιο απενεργοποιημένου Bluetooth",
        "_r2": "ΠΜ/ΜΜ",
        "_r3": "Δευτερόλεπτα",

        "_wi": "Εικονίδιο καιρού + 2 πεδία",
        "_3f": "3 πεδία",
        "_3p": "Γραμμή προόδου + 3 πεδία",

        "_f920": "Πρόοδος μπαταρίας",

        "_tr": "👉 ΣΥΝΤΟΜΕΎΣΕΙΣ ΑΦΗΣ",
        "_tc": "🎨 ΧΡΏΜΑΤΑ / ΦΌΝΤΟ",
        "_tt": "🔤 ΓΡΑΜΜΑΤΟΣΕΙΡΈΣ",
        "_ta": "🖼️ ΡΥΘΜΊΣΕΙΣ AOD (πάντα αναμμένη οθόνη)",
        "_to": "💡 ΆΛΛΑ",
        "_tx": "➡️ ΜΕΤΑΤΟΠΊΣΕΙΣ",
        "_t1": "Συντόμευση αφής ώρα",
        "_t2": "Συντόμευση αφής λεπτό",

        "_fs": "Γραμματοσειρά κειμένου",
        "_ts": "Μέγεθος γραμματοσειράς κειμένου (μόνο αυξομειώσιμες γραμματοσειρές)",
       
        "_fn": "Γραμματοσειρά ώρας",
        "_fnM": "Γραμματοσειρά λεπτού",
        "_fnA": "Γραμματοσειρά χρόνου AOD",
        "_fnS": "Μέγεθος γραμματοσειράς χρόνου",

        "_ox": "Μετατόπιση X χρόνου (50=κέντρο)",
        "_oy": "Μετατόπιση Y χρόνου (50=κέντρο)",
        "_gradientq": "Ποιότητα διαβάθμισης",
        "ng": "Χωρίς διαβάθμιση",
        "_pc": "Χρώμα κειμένου",
        "_ic": "Χρώμα ετικέτας",
       
        
        "_bgc": "Χρώμα φόντου",
        "_hc1": "Χρώμα ώρας",
        "_hc2": "Χρώμα ώρας 2",
        "_m1": "Χρώμα λεπτού",
        "_m2": "Χρώμα λεπτού 2",
        "_dc": "Χρώμα διαχωριστή",
        "_aas": "Δευτερόλεπτα πάντα αναμμένα",
        "_aod": "Λειτουργία AOD (πάντα αναμμένη οθόνη)",
        "_aodct": "Χρώμα απόχρωσης χρόνου AOD",
        "_aodc": "Χρώμα απόχρωσης δεδομένων AOD",
        "_aodT": "Φωτεινότητα χρόνου AOD",
        "_aodD": "Φωτεινότητα δεδομένων AOD. Αν η οθόνη σβήνει κατά τη διάρκεια AOD, μειώστε αυτόν τον αριθμό. Χαμηλότερος αριθμός = λιγότερη κατανάλωση μπαταρίας αλλά λιγότερο φωτεινό. Δείτε FAQ)",
        "_aodS": "Μετατόπιση AOD - αριθμός εικονοστοιχείων που η οθόνη μετατοπίζεται τυχαία κάθε λεπτό για αποφυγή καψίματος)",
        "_f20": "Δεδομένα πεδίου AOD",
        "_l20": "Ετικέτα πεδίου AOD",
        "ad0": "Απενεργοποίηση οθόνης",
        "ad100": "Πλήρες AOD (προεπιλογή)",
        "ad1": "Μόνο χρόνος",
        "ad3": "Μόνο χρόνος - κινούμενος",
        "ad4": "Χρόνος + πεδίο δεδομένων (επιλέξτε παρακάτω)",
        "ad6": "Χρόνος κινούμενος + πεδίο δεδομένων"
    }
}
