{
    "settings" : {
          "_theme": "Teema",
            "_preset": "Esiasetukset (Tallenna/Lataa asetuksesi)",
            "_timeF": "Ajan muoto (aika)",
            "_dateF": "Päivämäärän muoto",
            "_bgs": "Kehyksen (ulkoreunan) tyyli",
            "_presa": "Painenuolen tiedot ( -*- Nuolen ensimmäinen osa | Nuolen viimeinen osa)",
            "_presd": "Paineen ero ylös tai alas näyttämiseksi",
            "_presu": "Paineen päivitystiheys",
            "_batt": "Akun kuvake",
            "_alarm": "Hälytyksen kuvake",
            "_touch": "Ota kosketys käyttöön (kosketus = pidä 3 sekuntia)",
            "_touch0": "Tunnin kosketuspikakuvake",
            "_touch1": "Minuutin kosketuspikakuvake",
            "_touch2": "Ylärivi kosketuspikakuvake",
            "_touch3": "2. rivi (tiedot) kosketuspikakuvake",
            "_touch4": "Alarivi kosketuspikakuvake",
            "_f0": "Ylärivin tiedot",
            "_f1": "Rivin 2 tiedot",
            "_f3": "Alarivin (päivämäärä) tiedot",
            "_f2": "Alatekstin tiedot",
            "_m0": "Merkinnän 1 tiedot",
            "_m1": "Merkinnän 2 tiedot",
            "_bgsc": "Kehyksen väri",
            "_bgc": "Taustan väri",
            "_bglc": "Taustaviivan väri",
            "_ic": "Yläkuvakkeiden ajan väri (rivi 1)",
            "_pc": "Tietojen väri (rivi 2)",
            "_hc": "Ajan väri (rivi 3)",
            "_dc": "Päivämäärän väri (rivi 4)",
            "_btc": "Alatekstin väri",
            "_mc0": "Merkinnän 1 väri",
            "_mc1": "Merkinnän 2 väri",
            "_t_guf": " 📖 TAVOITTEET/YKSIKÖT/MUODOT "
    }
}