{
    "settings": {

        "_s67": "67 67（在下面設置）",
        "_o5": "自訂時間值（6767觸控快捷方式）",

        "_md1": "標記1資料",
        "_md2": "標記2資料",


                "_bd1": "錶盤大點尺寸",
        "_bd2": "錶盤小點尺寸",
        "_dc1": "錶盤大點顏色",
        "_dc2": "錶盤小點顏色",

        "_ps0": "常規錶盤",
        "_ps1": "完整進度",
        "_ps2": "秒標記作為進度",

        "_rainbow": "彩虹色",
        "_xmas": "聖誕色",

        "_f9": "錶盤進度",
        "_p9": "錶盤進度樣式",

        "_f1": "頂部資料",
        "_l1": "頂部標籤",
        "_p1": "頂部進度樣式",

        "_f2": "第1列左側資料",
        "_l2": "第1列左側標籤",
        "_p2": "第1列左側進度樣式",

        "_f3": "第1列中間資料",
        "_l3": "第1列中間標籤",
        "_p3": "第1列中間進度樣式",

        "_f4": "第1列右側資料",
        "_l4": "第1列右側標籤",
        "_p4": "第1列右側進度樣式",

        "_f5": "第2列左側資料",
        "_l5": "第2列左側標籤",
        "_p5": "第2列左側進度樣式",

        "_f6": "第2列中間資料",
        "_l6": "第2列中間標籤",
        "_p6": "第2列中間進度樣式",

        "_f7": "第2列右側資料",
        "_l7": "第2列右側標籤",
        "_p7": "第2列右側進度樣式",

        "_f8": "底部資料",
        "_l8": "底部標籤",
        "_p8": "底部進度樣式",

        "_f20": "AOD欄位資料",
        "_l20": "AOD欄位標籤",

        "_hc1": "小時顏色1",
        "_hc2": "小時顏色2",


        "_mc1": "分鐘顏色1",
        "_mc2": "分鐘顏色2",


        "_dv1": "分隔線顏色",



        "_sbg" : "與背景色相同",

        "_m1": "標記1顏色",
        "_m2": "標記2顏色",
        
        "_cp1": "頂部進度顏色1",
        "_c21": "頂部進度顏色2",
        "_cu1": "頂部進度未填充顏色",

        "_cp2": "底部進度顏色1",
        "_c22": "底部進度顏色2",
        "_cu2": "底部進度未填充顏色",

        "_bgc": "背景顏色",
        "_bgl": "背景線條顏色",
        "_cs": "深70%",
        "_cpbs" : "與頂部進度條相同",

        "_stc" : "與文字顏色相同",
        "_slc" : "與標籤顏色相同",


        "_c1": "頂部資料顏色",
        "_c1l": "頂部標籤顏色",

        "_c2": "第1列資料顏色",
        "_c2l": "第1列標籤顏色",

        "_c3": "第2列資料顏色",
        "_c3l": "第2列標籤顏色",

        "_c4": "底部資料顏色",
        "_c4l": "底部標籤顏色",

        "_c5": "頂部進度資料顏色",
        "_c5l": "頂部進度標籤顏色",

        "_c6": "底部進度資料顏色",
        "_c6l": "底部進度標籤顏色",
        "_x4": "載入前一個預設",
        "_x3": "載入前一個主題",

        "_pb1": "資料進度條已填充顏色",
        "_pb2": "資料進度條未填充顏色",

        "_rst": "重設所有設定",
        "_tr": "👉 觸控捷徑",
        "_tc": "🎨 顏色 / 背景",
        "_tt": "🔤 字型",
        "_ta": "🖼️ AOD設定（永遠顯示）",
        "_to": "💡 其他",
        "_tx": "➡️ 偏移",

        "_o1": "時間偏移（X小時，Y小時，X分鐘，Y分鐘）預設：20",
        "_o2": "欄位X偏移（頂部，第1列左，第1列中，第1列右，第2列左，第2列中，第2列右，底部）預設：20",
        "_o3": "欄位Y偏移（頂部，第1列左，第1列中，第1列右，第2列左，第2列中，第2列右，底部）預設：20",
        "_o4": "標籤Y偏移（第1列左，第1列中，第1列右，第2列左，第2列中，第2列右）預設：20",
        "_bdb": "繪製數字背景（分鐘更清晰，小時不顯示在後面）",

        "_t1": "時間字型",
        "_t1a": "時間字型AOD",
        "_t1s": "時間字型大小",


        "_sah": "與小時相同",

        "_t3": "文字字型",
        "_s1": "頂部文字字型大小（僅可調整大小的字型）",
        "_s2": "第1列字型大小",
        "_s3": "第2列字型大小",
        "_s4": "底部字型大小",
    
        "_fo": "輪廓（如果可用）",
        "_fk": "保持不變",
        "_fks": "保持不變，包括內部",


        "_pc": "文字顏色",
        "_ic": "標籤顏色",      

        "_gq": "漸層品質",
        "_ng": "無漸層",

        "_0f" : "顯示欄位進度",
        "_1f" : "完整",
        "_2f" : "空",
        "_3f" : "隱藏",

        "_x2": "載入下一個主題",
        
        "_a1": "觸控捷徑左",
        "_a2": "觸控捷徑中",
        "_a3": "觸控捷徑右",

        "_aas": "始終顯示秒",
        "_aod": "AOD模式（永遠顯示）",
        "_aodct": "AOD時間色調",
        "_aodc": "AOD資料色調",
        "_aodT": "AOD時間亮度",
        "_aodD": "AOD資料亮度（如果AOD期間螢幕關閉，請降低此數值。數值越低=電池消耗越少但亮度越低。查看FAQ）",
        "_aodS": "AOD偏移（每分鐘螢幕隨機偏移的像素數以防止烙印）",
        "ad0": "關閉螢幕",
        "ad100": "完整AOD（預設）",
        
        "ad1": "僅時間",
        "ad3": "僅時間 - 移動",
        "ad4": "時間 + 資料欄位（在下方選擇）",
        "ad6": "時間移動 + 資料欄位"
    }
}
